{"player_401_001.png":{"spriteOffset":[0,0],"spriteSize":[120,120],"spriteSourceSize":[120,120],"textureRect":{"pos":[131,1],"size":[120,120]},"textureRotated":false},"player_401_2_001.png":{"spriteOffset":[0,4],"spriteSize":[86,26],"spriteSourceSize":[86,34],"textureRect":{"pos":[1,131],"size":[86,26]},"textureRotated":false},"player_401_extra_001.png":{"spriteOffset":[0,-28],"spriteSize":[102,38],"spriteSourceSize":[102,94],"textureRect":{"pos":[131,123],"size":[102,38]},"textureRotated":false},"player_401_glow_001.png":{"spriteOffset":[0,0],"spriteSize":[128,128],"spriteSourceSize":[128,128],"textureRect":{"pos":[1,1],"size":[128,128]},"textureRotated":false}}