{"player_ball_13_001.png":{"spriteOffset":[0,0],"spriteSize":[140,140],"spriteSourceSize":[140,140],"textureRect":{"pos":[152,2],"size":[140,140]},"textureRotated":false},"player_ball_13_2_001.png":{"spriteOffset":[0,0],"spriteSize":[96,132],"spriteSourceSize":[96,132],"textureRect":{"pos":[294,2],"size":[96,132]},"textureRotated":false},"player_ball_13_glow_001.png":{"spriteOffset":[0,0],"spriteSize":[148,148],"spriteSourceSize":[148,148],"textureRect":{"pos":[2,2],"size":[148,148]},"textureRotated":false}}