{"player_127_001.png":{"spriteOffset":[0,0],"spriteSize":[126,120],"spriteSourceSize":[126,120],"textureRect":{"pos":[2,132],"size":[126,120]},"textureRotated":false},"player_127_2_001.png":{"spriteOffset":[0,14],"spriteSize":[110,78],"spriteSourceSize":[110,106],"textureRect":{"pos":[130,132],"size":[110,78]},"textureRotated":true},"player_127_extra_001.png":{"spriteOffset":[0,-7],"spriteSize":[120,68],"spriteSourceSize":[120,82],"textureRect":{"pos":[138,2],"size":[120,68]},"textureRotated":true},"player_127_glow_001.png":{"spriteOffset":[0,0],"spriteSize":[134,128],"spriteSourceSize":[134,128],"textureRect":{"pos":[2,2],"size":[134,128]},"textureRotated":false}}