{"player_ball_115_001.png":{"spriteOffset":[0,0],"spriteSize":[140,140],"spriteSourceSize":[140,140],"textureRect":{"pos":[152,2],"size":[140,140]},"textureRotated":false},"player_ball_115_2_001.png":{"spriteOffset":[0,0],"spriteSize":[82,78],"spriteSourceSize":[82,78],"textureRect":{"pos":[294,94],"size":[82,78]},"textureRotated":false},"player_ball_115_extra_001.png":{"spriteOffset":[0,0],"spriteSize":[80,90],"spriteSourceSize":[80,90],"textureRect":{"pos":[294,2],"size":[80,90]},"textureRotated":false},"player_ball_115_glow_001.png":{"spriteOffset":[0,0],"spriteSize":[148,148],"spriteSourceSize":[148,148],"textureRect":{"pos":[2,2],"size":[148,148]},"textureRotated":false}}