{"player_ball_76_001.png":{"spriteOffset":[0,0],"spriteSize":[144,144],"spriteSourceSize":[144,144],"textureRect":{"pos":[1,155],"size":[144,144]},"textureRotated":false},"player_ball_76_2_001.png":{"spriteOffset":[0,0],"spriteSize":[134,134],"spriteSourceSize":[134,134],"textureRect":{"pos":[147,155],"size":[134,134]},"textureRotated":false},"player_ball_76_extra_001.png":{"spriteOffset":[0,0],"spriteSize":[132,130],"spriteSourceSize":[132,130],"textureRect":{"pos":[155,1],"size":[132,130]},"textureRotated":true},"player_ball_76_glow_001.png":{"spriteOffset":[0,0],"spriteSize":[152,152],"spriteSourceSize":[152,152],"textureRect":{"pos":[1,1],"size":[152,152]},"textureRotated":false}}