{"player_425_001.png":{"spriteOffset":[2,0],"spriteSize":[133,122],"spriteSourceSize":[137,122],"textureRect":{"pos":[133,1],"size":[133,122]},"textureRotated":true},"player_425_2_001.png":{"spriteOffset":[1,0],"spriteSize":[125,112],"spriteSourceSize":[127,112],"textureRect":{"pos":[133,136],"size":[125,112]},"textureRotated":false},"player_425_extra_001.png":{"spriteOffset":[1,10],"spriteSize":[125,74],"spriteSourceSize":[127,94],"textureRect":{"pos":[1,144],"size":[125,74]},"textureRotated":false},"player_425_glow_001.png":{"spriteOffset":[2,0],"spriteSize":[141,130],"spriteSourceSize":[145,130],"textureRect":{"pos":[1,1],"size":[141,130]},"textureRotated":true}}