{"player_ball_101_001.png":{"spriteOffset":[0,0],"spriteSize":[140,142],"spriteSourceSize":[140,142],"textureRect":{"pos":[153,1],"size":[140,142]},"textureRotated":false},"player_ball_101_2_001.png":{"spriteOffset":[0,0],"spriteSize":[114,114],"spriteSourceSize":[114,114],"textureRect":{"pos":[295,1],"size":[114,114]},"textureRotated":false},"player_ball_101_extra_001.png":{"spriteOffset":[0,0],"spriteSize":[68,68],"spriteSourceSize":[68,68],"textureRect":{"pos":[411,1],"size":[68,68]},"textureRotated":false},"player_ball_101_glow_001.png":{"spriteOffset":[0,0],"spriteSize":[148,150],"spriteSourceSize":[148,150],"textureRect":{"pos":[1,1],"size":[148,150]},"textureRotated":true}}